msgpassing/__init__.py
msgpassing/frontend/build/asset-manifest.json
msgpassing/frontend/build/bootstrap.min.css
msgpassing/frontend/build/index.html
msgpassing/frontend/build/static/js/main.181c19a3.js
msgpassing/frontend/build/static/js/main.181c19a3.js.LICENSE.txt
msgpassing/frontend/build/static/js/main.181c19a3.js.map
streamlit_message_passing-0.1.1.dist-info/METADATA
streamlit_message_passing-0.1.1.dist-info/WHEEL
streamlit_message_passing-0.1.1.dist-info/RECORD
