Metadata-Version: 2.1
Name: streamlit-message-passing
Version: 0.1.1
Summary: Streamlit component for doing message passing between parent window and server via JS
Author: Damián Silvani
Author-email: munshkr@gmail.com
Requires-Python: >=3.9,<4.0
Classifier: Programming Language :: Python :: 3
Classifier: Programming Language :: Python :: 3.9
Classifier: Programming Language :: Python :: 3.10
Classifier: Programming Language :: Python :: 3.11
Requires-Dist: streamlit (>=0.63)
